commitaid/__init__.py
commitaid/cli.py
commitaid/config.py
commitaid/test.py
commitaid/workflow.py
commitaid-0.1.1.dist-info/licenses/LICENSE
commitaid-0.1.1.dist-info/METADATA
commitaid-0.1.1.dist-info/WHEEL
commitaid-0.1.1.dist-info/entry_points.txt
commitaid-0.1.1.dist-info/top_level.txt
commitaid-0.1.1.dist-info/RECORD
