Metadata-Version: 2.4
Name: commitaid
Version: 0.1.1
Summary: AI-powered Git commit message generator using Claude
Author-email: Michal Vavrinec <mvavrine@redhat.com>
Project-URL: Homepage, https://github.com/Ruclo/commitaid
Classifier: Programming Language :: Python :: 3
Classifier: License :: OSI Approved :: MIT License
Classifier: Operating System :: OS Independent
Requires-Python: >=3.8
License-File: LICENSE
Dynamic: license-file
